shipitapi/__init__.py
shipitapi/shipitapi.py
shipitapi-3.1.0.dist-info/LICENSE
shipitapi-3.1.0.dist-info/METADATA
shipitapi-3.1.0.dist-info/WHEEL
shipitapi-3.1.0.dist-info/top_level.txt
shipitapi-3.1.0.dist-info/RECORD
