Metadata-Version: 2.1
Name: shipitapi
Version: 3.1.0
Summary: Lib package to facilitate access to Ship IT API operations
Home-page: https://github.com/MihaiTabara/shipitapi
Author: Mihai Tabara
Author-email: mtabara@mozilla.com
License: MPL
Keywords: shipit api lib package
Platform: UNKNOWN
Requires-Dist: certifi
Requires-Dist: mohawk
Requires-Dist: redo
Requires-Dist: requests
